<?xml version="1.0" encoding="UTF-8"?>
<record_update table="sp_row">
    <sp_row action="INSERT_OR_UPDATE">
        <class_name/>
        <order>1</order>
        <sp_column/>
        <sp_container display_value="Categories v2 - Container 1">0d3779eadb101740fbaa7d668c9619c9</sp_container>
        <sys_class_name>sp_row</sys_class_name>
        <sys_created_by>arjun</sys_created_by>
        <sys_created_on>2018-02-18 11:46:26</sys_created_on>
        <sys_id>3e37f9eadb101740fbaa7d668c961943</sys_id>
        <sys_mod_count>0</sys_mod_count>
        <sys_name>1</sys_name>
        <sys_package display_value="esm_sp_esm_main" source="x_infte_esm_sp_esm">3a8ff870dbc41b00fbaa7d668c9619ff</sys_package>
        <sys_policy/>
        <sys_scope display_value="esm_sp_esm_main">3a8ff870dbc41b00fbaa7d668c9619ff</sys_scope>
        <sys_update_name>sp_row_3e37f9eadb101740fbaa7d668c961943</sys_update_name>
        <sys_updated_by>arjun</sys_updated_by>
        <sys_updated_on>2018-02-18 11:46:26</sys_updated_on>
    </sp_row>
</record_update>
